scalign/__init__.py
scalign/reference.py
scalign-0.1.3.dist-info/METADATA
scalign-0.1.3.dist-info/WHEEL
scalign-0.1.3.dist-info/top_level.txt
scalign-0.1.3.dist-info/RECORD
