Metadata-Version: 2.2
Name: scalign
Version: 0.1.3
Summary: align query dataset to reference atlases.
Author: Zheng Yang
Author-email: xornent@outlook.com
License: MIT
Requires-Python: >= 3.6
Requires-Dist: scalign-umap<0.2.1,>=0.2.0
Requires-Dist: scvi-tools>=1.3.0
Requires-Dist: scanpy
Requires-Dist: pandas
Requires-Dist: numpy
Requires-Dist: matplotlib
Requires-Dist: seaborn
Provides-Extra: parametric
Requires-Dist: tensorflow>=2.1; extra == "parametric"
Requires-Dist: keras>=3.0; extra == "parametric"
Dynamic: author
Dynamic: author-email
Dynamic: license
Dynamic: provides-extra
Dynamic: requires-dist
Dynamic: requires-python
Dynamic: summary
